data_utils/annotate_mgfs.py
data_utils/feature_extractor.py
depthcharge/__init__.py
depthcharge/masses.py
depthcharge/similarity.py
depthcharge/utils.py
depthcharge/version.py
depthcharge/components/__init__.py
depthcharge/components/encoders.py
depthcharge/components/feedforward.py
depthcharge/components/mixins.py
depthcharge/components/transformers.py
depthcharge/data/__init__.py
depthcharge/data/datasets.py
depthcharge/data/dia_io.py
depthcharge/data/hdf5.py
depthcharge/data/loaders.py
depthcharge/data/parsers.py
depthcharge/data/preprocessing.py
depthcharge/models/__init__.py
depthcharge/models/denovo/__init__.py
depthcharge/models/denovo/model.py
diffnovo_dia/__init__.py
diffnovo_dia/config.yaml
diffnovo_dia/diffnovo_dia.py
diffnovo_dia/utils.py
diffnovo_dia/version.py
diffnovo_dia/data/__init__.py
diffnovo_dia/data/datasets.py
diffnovo_dia/data/ms_io.py
diffnovo_dia/denovo/__init__.py
diffnovo_dia/denovo/dataloaders.py
diffnovo_dia/denovo/evaluate.py
diffnovo_dia/denovo/model.py
diffnovo_dia/denovo/model_runner.py
diffnovo_dia-0.1.2.dist-info/licenses/LICENSE
diffnovo_dia-0.1.2.dist-info/METADATA
diffnovo_dia-0.1.2.dist-info/WHEEL
diffnovo_dia-0.1.2.dist-info/entry_points.txt
diffnovo_dia-0.1.2.dist-info/top_level.txt
diffnovo_dia-0.1.2.dist-info/RECORD
